conventional_commits/__init__.py
conventional_commits/message.py
conventional_commits/parser.py
conventionalcommits-0.1.0.dist-info/METADATA
conventionalcommits-0.1.0.dist-info/WHEEL
conventionalcommits-0.1.0.dist-info/top_level.txt
conventionalcommits-0.1.0.dist-info/RECORD
