Metadata-Version: 2.2
Name: ConventionalCommits
Version: 0.1.0
Requires-Python: >=3.10
Requires-Dist: PySerials<0.2,>=0.1
